llama_dashboard/__init__.py
llama_dashboard/app.py
llama_dashboard/config.py
llama_dashboard/core.py
llama_dashboard/data_sources.py
llama_dashboard-0.1.0.dist-info/METADATA
llama_dashboard-0.1.0.dist-info/WHEEL
llama_dashboard-0.1.0.dist-info/entry_points.txt
llama_dashboard-0.1.0.dist-info/licenses/LICENSE
llama_dashboard-0.1.0.dist-info/RECORD
