Metadata-Version: 2.4
Name: llama-dashboard
Version: 0.1.0
Summary: Web dashboard for monitoring and interacting with the LlamaAI Ecosystem.
Project-URL: Homepage, https://github.com/yourusername/llama-dashboard-pkg
Project-URL: Bug Tracker, https://github.com/yourusername/llama-dashboard-pkg/issues
Project-URL: Documentation, https://yourusername.github.io/llama-dashboard-pkg/
Author-email: Your Name <your.email@example.com>
License: MIT License
License-File: LICENSE
Classifier: Development Status :: 3 - Alpha
Classifier: Intended Audience :: Developers
Classifier: Intended Audience :: End Users/Desktop
Classifier: License :: OSI Approved :: MIT License
Classifier: Programming Language :: Python :: 3
Classifier: Programming Language :: Python :: 3.8
Classifier: Programming Language :: Python :: 3.9
Classifier: Programming Language :: Python :: 3.10
Classifier: Programming Language :: Python :: 3.11
Classifier: Topic :: Internet :: WWW/HTTP :: Dynamic Content :: CGI Tools/Libraries
Classifier: Topic :: Scientific/Engineering :: Artificial Intelligence
Classifier: Topic :: Scientific/Engineering :: Visualization
Classifier: Topic :: Software Development :: Libraries :: Python Modules
Requires-Python: >=3.8
Requires-Dist: cryptography>=3.4.6
Requires-Dist: httpx>=0.24.0
Requires-Dist: loguru>=0.7.0
Requires-Dist: numpy>=1.21.0
Requires-Dist: pandas>=1.5.0
Requires-Dist: pydantic>=1.10.0
Requires-Dist: streamlit>=1.20.0
Provides-Extra: all
Requires-Dist: azure-cosmos>=4.0.0; extra == 'all'
Requires-Dist: azure-storage-blob>=12.10.0; extra == 'all'
Requires-Dist: black>=23.3.0; extra == 'all'
Requires-Dist: google-auth>=2.0.0; extra == 'all'
Requires-Dist: google-cloud-bigquery>=3.0.0; extra == 'all'
Requires-Dist: google-cloud-firestore>=2.0.0; extra == 'all'
Requires-Dist: google-cloud-storage>=2.0.0; extra == 'all'
Requires-Dist: httpx; extra == 'all'
Requires-Dist: isort>=5.12.0; extra == 'all'
Requires-Dist: mkdocs-material>=9.1.6; extra == 'all'
Requires-Dist: mkdocs>=1.4.2; extra == 'all'
Requires-Dist: mkdocstrings[python]>=0.20.0; extra == 'all'
Requires-Dist: mlx>=0.6.0; extra == 'all'
Requires-Dist: mypy>=1.2.0; extra == 'all'
Requires-Dist: pre-commit>=3.3.1; extra == 'all'
Requires-Dist: pyodbc>=4.0.0; extra == 'all'
Requires-Dist: pytest-cov>=4.1.0; extra == 'all'
Requires-Dist: pytest-mock>=3.10.0; extra == 'all'
Requires-Dist: pytest>=7.3.1; extra == 'all'
Requires-Dist: ruff>=0.0.260; extra == 'all'
Provides-Extra: azure
Requires-Dist: azure-cosmos>=4.0.0; extra == 'azure'
Requires-Dist: azure-storage-blob>=12.10.0; extra == 'azure'
Requires-Dist: pyodbc>=4.0.0; extra == 'azure'
Provides-Extra: dev
Requires-Dist: black>=23.3.0; extra == 'dev'
Requires-Dist: httpx; extra == 'dev'
Requires-Dist: isort>=5.12.0; extra == 'dev'
Requires-Dist: mypy>=1.2.0; extra == 'dev'
Requires-Dist: pre-commit>=3.3.1; extra == 'dev'
Requires-Dist: pytest-cov>=4.1.0; extra == 'dev'
Requires-Dist: pytest-mock>=3.10.0; extra == 'dev'
Requires-Dist: pytest>=7.3.1; extra == 'dev'
Requires-Dist: ruff>=0.0.260; extra == 'dev'
Provides-Extra: docs
Requires-Dist: mkdocs-material>=9.1.6; extra == 'docs'
Requires-Dist: mkdocs>=1.4.2; extra == 'docs'
Requires-Dist: mkdocstrings[python]>=0.20.0; extra == 'docs'
Provides-Extra: gcp
Requires-Dist: google-auth>=2.0.0; extra == 'gcp'
Requires-Dist: google-cloud-bigquery>=3.0.0; extra == 'gcp'
Requires-Dist: google-cloud-firestore>=2.0.0; extra == 'gcp'
Requires-Dist: google-cloud-storage>=2.0.0; extra == 'gcp'
Provides-Extra: mlx
Requires-Dist: mlx>=0.6.0; extra == 'mlx'
Provides-Extra: security
